pointpare/__init__.py
pointpare-0.1.0.dist-info/LICENSE.txt
pointpare-0.1.0.dist-info/METADATA
pointpare-0.1.0.dist-info/WHEEL
pointpare-0.1.0.dist-info/top_level.txt
pointpare-0.1.0.dist-info/RECORD
