Metadata-Version: 2.1
Name: pointpare
Version: 0.1.0
Summary: A simple package for paring together points.
Home-page: https://github.com/hsorby/pointpare
Author: Hugh Sorby
Author-email: h.sorby@auckland.ac.nz
License: Apache
Platform: any
Classifier: Development Status :: 4 - Beta
Classifier: Programming Language :: Python
Classifier: License :: OSI Approved :: Apache Software License
Classifier: Programming Language :: Python :: 3.8
Requires-Python: >=3.8
License-File: LICENSE.txt
Provides-Extra: testing
Requires-Dist: setuptools ; extra == 'testing'
Requires-Dist: coverage ; extra == 'testing'
